{
  "id": "siman-004",
  "chapterLabel": "סימן ד",
  "title": "ברכות התורה",
  "sections": [
    {
      "id": "siman-004-seif-001",
      "section": 1,
      "text": "חובת ברכות התורה היא מן התורה. כל מי שמתחיל ללמוד תורה חייב לברך תחילה ברכות התורה. נוסח הברכה: 'אשר בחר בנו מכל העמים ונתן לנו את תורתו'."
    },
    {
      "id": "siman-004-seif-002",
      "section": 2,
      "text": "לפי מנהג הספרדים, מברכים ברכות התורה כל בוקר לאחר נטילת ידיים וברכות השחר. הברכה כוללת שלושה חלקים: 'לעסוק בדברי תורה', 'אשר בחר בנו', ו'תן חלקנו בתורתך'."
    },
    {
      "id": "siman-004-seif-003",
      "section": 3,
      "text": "יש לברך ברכות התורה לפני כל לימוד תורה, בין אם תורה שבכתב ובין תורה שבעל פה. גם קריאת תהילים צריכה ברכות התורה. לפי הרב עובדיה יוסף, אם ישן שינת קבע ביום, צריך לברך שוב ברכות התורה."
    }
  ],
  "version": 1
}
